pybaselines/__init__.py
pybaselines/_algorithm_setup.py
pybaselines/_banded_utils.py
pybaselines/_compat.py
pybaselines/_spline_utils.py
pybaselines/_validation.py
pybaselines/_weighting.py
pybaselines/api.py
pybaselines/classification.py
pybaselines/misc.py
pybaselines/morphological.py
pybaselines/optimizers.py
pybaselines/polynomial.py
pybaselines/smooth.py
pybaselines/spline.py
pybaselines/utils.py
pybaselines/whittaker.py
pybaselines/two_d/__init__.py
pybaselines/two_d/_algorithm_setup.py
pybaselines/two_d/_spline_utils.py
pybaselines/two_d/_whittaker_utils.py
pybaselines/two_d/api.py
pybaselines/two_d/morphological.py
pybaselines/two_d/optimizers.py
pybaselines/two_d/polynomial.py
pybaselines/two_d/smooth.py
pybaselines/two_d/spline.py
pybaselines/two_d/whittaker.py
pybaselines-1.1.0.dist-info/LICENSE.txt
pybaselines-1.1.0.dist-info/LICENSES_bundled.txt
pybaselines-1.1.0.dist-info/METADATA
pybaselines-1.1.0.dist-info/WHEEL
pybaselines-1.1.0.dist-info/top_level.txt
pybaselines-1.1.0.dist-info/RECORD
