Metadata-Version: 2.1
Name: pybaselines
Version: 1.1.0
Summary: A library of algorithms for the baseline correction of experimental data.
Author-email: Donald Erb <donnie.erb@gmail.com>
License: BSD 3-Clause License
Project-URL: Homepage, https://github.com/derb12/pybaselines
Project-URL: Documentation, https://pybaselines.readthedocs.io
Keywords: materials characterization,materials science,baseline,background,baseline correction,baseline subtraction,chemistry,spectroscopy,raman
Classifier: Development Status :: 5 - Production/Stable
Classifier: Intended Audience :: Science/Research
Classifier: Intended Audience :: Developers
Classifier: License :: OSI Approved :: BSD License
Classifier: Operating System :: OS Independent
Classifier: Programming Language :: Python :: 3
Classifier: Programming Language :: Python :: 3.8
Classifier: Programming Language :: Python :: 3.9
Classifier: Programming Language :: Python :: 3.10
Classifier: Programming Language :: Python :: 3.11
Classifier: Programming Language :: Python :: 3.12
Classifier: Topic :: Scientific/Engineering
Classifier: Topic :: Scientific/Engineering :: Chemistry
Classifier: Topic :: Scientific/Engineering :: Information Analysis
Classifier: Topic :: Scientific/Engineering :: Physics
Requires-Python: >=3.8
License-File: LICENSE.txt
License-File: LICENSES_bundled.txt
Requires-Dist: numpy >=1.20
Requires-Dist: scipy >=1.5
Provides-Extra: dev
Requires-Dist: pybaselines[docs,full,release,test] ; extra == 'dev'
Provides-Extra: docs
Requires-Dist: sphinx ; extra == 'docs'
Requires-Dist: sphinx-rtd-theme ; extra == 'docs'
Requires-Dist: sphinx-autoapi ; extra == 'docs'
Requires-Dist: sphinx-gallery ; extra == 'docs'
Requires-Dist: matplotlib ; extra == 'docs'
Requires-Dist: numpydoc ; extra == 'docs'
Provides-Extra: full
Requires-Dist: pentapy >=1.1 ; extra == 'full'
Requires-Dist: numba >=0.49 ; extra == 'full'
Provides-Extra: release
Requires-Dist: build ; extra == 'release'
Requires-Dist: bump-my-version ; extra == 'release'
Requires-Dist: twine ; extra == 'release'
Provides-Extra: test
Requires-Dist: pytest ; extra == 'test'
Requires-Dist: ruff ; extra == 'test'
